xiaomeilv/__init__.py
xiaomeilv/xiaomeilv.py
xiaomeilv-0.0.1.dist-info/LICENSE.txt
xiaomeilv-0.0.1.dist-info/METADATA
xiaomeilv-0.0.1.dist-info/WHEEL
xiaomeilv-0.0.1.dist-info/top_level.txt
xiaomeilv-0.0.1.dist-info/RECORD
