Metadata-Version: 2.1
Name: xiaomeilv
Version: 0.0.1
Summary: just a test demo
Home-page: https://github.com/jiajieyuan1010/kaggle
Author: xiaomeilv
Author-email: jiajieyuan666@gmail.com
License: UNKNOWN
Platform: UNKNOWN
Classifier: Programming Language :: Python :: 3
Classifier: License :: OSI Approved :: MIT License
Classifier: Operating System :: OS Independent
Requires-Python: >=3.6
